Metadata-Version: 1.1
Name: python-meijer
Version: 0.1.0
Summary: A python wrapper for the Meijer API
Home-page: https://github.com/sllawcj/python_Meijer
Author: sllawcj
Author-email: cjsllaw@gmail.com
License: MIT
Platform: UNKNOWN
Classifier: Development Status :: 4 - Beta
Classifier: Intended Audience :: Science/Research
Classifier: License :: OSI Approved :: BSD License
Classifier: Operating System :: POSIX :: Linux
Classifier: Programming Language :: Python :: 2
Classifier: Programming Language :: Python :: 2.7
Classifier: Programming Language :: Python :: 3
Classifier: Programming Language :: Python :: 3.4
Classifier: Programming Language :: Python :: 3.5
